contador_2b/contador_2b.v
module contador_2b(
	input wire clk, up,
	input rst,
	output reg [1:0] curr_numero
);

reg [1:0] next_numero;
localparam [1:0] 	b0 = 2'b00,
					b1 = 2'b01,
					b2 = 2'b10,
					b3 = 2'b11;

reg enable_up = 1; // enable para cuando se suelta el boton 


always @(posedge clk) begin

	if (rst) curr_numero <= b0;

	if(up) begin
		if(enable_up)
			begin
				curr_numero <= next_numero;
				enable_up <= 0;
			end
	end else
		enable_up <= 1;
end

always @*
	case ({up,curr_numero})
	 //contando hacia arriba
		{1'b1,b0} : next_numero = b1;
		{1'b1,b1} : next_numero = b2;
		{1'b1,b2} : next_numero = b3;
		{1'b1,b3} : next_numero = b0;
		default : next_numero = curr_numero;
	
	endcase



endmodule

contador_2b/contador_2b_tb.v
`default_nettype none
`define DUMPSTR(x) `"x.vcd`"
`timescale 100 ns / 10 ns

module contador_2b_tb();

reg clk = 0;
always #0.5 clk = ~clk; //cada 0.5 unidades temporales se niega el clk

reg test_rst, test_down, test_up;
wire test_numero;

contador_2b UUT (//-- Instantiate the unit to test
	.clk(clk),
	.rst(test_rst),
	.up(test_up)
);


initial begin
	$dumpfile(`DUMPSTR(`VCD_OUTPUT));//-- File were to store the simulation results
	$dumpvars(0, contador_2b_tb);
	
	test_rst=1'b1;
	#1
	test_rst=1'b0;
	#1
	test_up=1'b1;
	#5
	test_rst=1'b1;
	#1
	test_rst=1'b0;
	#1
	test_up=1'b0;
	#1
	test_up=1'b1;
	#1
	test_up=1'b0;
	#1
	test_up=1'b1;
	#1
	test_up=1'b0;
	#1
	test_up=1'b1;
	#1
	test_up=1'b0;
	#1
	test_up=1'b1;
	#1
	test_up=1'b0;
	#1
	test_up=1'b1;
	#1
	test_up=1'b0;
	#1
	test_up=1'b1;
	#1
	test_up=1'b0;
	#20
	
	
	$finish;
end

endmodule

contador_2b/contador_2b_tb.vcd
$date
	Thu Jun 22 14:52:56 2023
$end
$version
	Icarus Verilog
$end
$timescale
	1ps
$end
$scope module contador_2b_tb $end
$var reg 1 ! clk $end
$var reg 1 " test_rst $end
$var reg 1 # test_up $end
$scope module UUT $end
$var wire 1 ! clk $end
$var wire 1 " rst $end
$var wire 1 # up $end
$var reg 2 $ curr_numero [1:0] $end
$var reg 1 % enable_up $end
$var reg 2 & next_numero [1:0] $end
$upscope $end
$upscope $end
$enddefinitions $end
#0
$dumpvars
bx &
1%
bx $
x#
1"
0!
$end
#50000
b0 &
b0 $
1!
#100000
0!
0"
#150000
1!
#200000
b1 &
0!
1#
#250000
b10 &
0%
b1 $
1!
#300000
0!
#350000
1!
#400000
0!
#450000
1!
#500000
0!
#550000
1!
#600000
0!
#650000
1!
#700000
0!
1"
#750000
b1 &
b0 $
1!
#800000
0!
0"
#850000
1!
#900000
b0 &
0!
0#
#950000
1%
1!
#1000000
b1 &
0!
1#
#1050000
b10 &
0%
b1 $
1!
#1100000
b1 &
0!
0#
#1150000
1%
1!
#1200000
b10 &
0!
1#
#1250000
b11 &
0%
b10 $
1!
#1300000
b10 &
0!
0#
#1350000
1%
1!
#1400000
b11 &
0!
1#
#1450000
b0 &
0%
b11 $
1!
#1500000
b11 &
0!
0#
#1550000
1%
1!
#1600000
b0 &
0!
1#
#1650000
b1 &
0%
b0 $
1!
#1700000
b0 &
0!
0#
#1750000
1%
1!
#1800000
b1 &
0!
1#
#1850000
b10 &
0%
b1 $
1!
#1900000
b1 &
0!
0#
#1950000
1%
1!
#2000000
b10 &
0!
1#
#2050000
b11 &
0%
b10 $
1!
#2100000
b10 &
0!
0#
#2150000
1%
1!
