mux_4b_4_1/mux_4b_4_1.v
module mux_4b_4_1(
	input wire [1:0] sel,
	input wire [3:0] d3, d2, d1, d0,
	output reg [3:0] f
);

	always @(d3 or d2 or d1 or d0 or sel)
		case (sel)
			2'b00 : f = d0;
			2'b01 : f = d1;
			2'b10 : f = d2;
			2'b11 : f = d3;
		endcase
	
endmodule

contador_2b/contador_2b.v
module contador_2b(
	input wire clk, up,
	input rst,
	output reg [1:0] curr_numero
);

reg [1:0] next_numero;
localparam [1:0] 	b0 = 4'b00,
					b1 = 4'b01,
					b2 = 4'b10,
					b3 = 4'b11;

reg enable_up = 1; // enable para cuando se suelta el boton 


always @(posedge clk) begin

	if (rst) curr_numero <= b0;

	if(up) begin
		if(enable_up)
			begin
				curr_numero <= next_numero;
				enable_up <= 0;
			end
	end else
		enable_up <= 1;
end

always @*
	case ({up,curr_numero})
	 //contando hacia arriba
		{1'b1,b0} : next_numero = b1;
		{1'b1,b1} : next_numero = b2;
		{1'b1,b2} : next_numero = b3;
		{1'b1,b3} : next_numero = b0;
		default : next_numero = curr_numero;
	
	endcase



endmodule

divisor_4b.v
`include "mux_4b_4_1/mux_4b_4_1.v"
`include "contador_2b/contador_2b.v"


module divisor_4b(
	input wire up, down, ok, clk, rst,
	output wire [3:0] leds
	);

wire [3:0] num, den, result, rest;
wire [1:0] sel;

//para probar
assign num = 4'b0001;
assign den = 4'b0010;
assign result = 4'b0100;
assign rest = 4'b1000;
//fin para probar


contador_2b contador_2b_0(
	.clk(clk),
	.up(ok),
	.rst(rst),
	.curr_numero(sel)
);

mux_4b_4_1 mux_4b_4_1_a_leds(
	.d0(num),
	.d1(den),
	.d2(result),
	.d3(rest),
	.f(leds),
	.sel(sel)
);

endmodule

divisor_4b_tb.v
`default_nettype none
`define DUMPSTR(x) `"x.vcd`"
`timescale 100 ns / 10 ns

module divisor_4b_tb();

reg clk = 0;
always #0.5 clk = ~clk; //cada 0.5 unidades temporales se niega el clk

reg test_rst, test_down, test_up, test_ok;
wire [3:0] test_leds;

divisor_4b UUT (//-- Instantiate the unit to test
	.clk(clk),
	.rst(test_rst),
	.down(test_down),
	.up(test_up),
	.ok(test_ok),
	.leds(test_leds)
);


initial begin
	$dumpfile(`DUMPSTR(`VCD_OUTPUT));//-- File were to store the simulation results
	$dumpvars(0, divisor_4b_tb);
	
	
	test_rst=1'b1;
	#1
	test_rst=1'b0;
	#5
	test_ok = 1'b1;
	#1
	test_ok = 1'b0;
	#1
	test_ok = 1'b1;
	#1
	test_ok = 1'b0;
	#1
	test_ok = 1'b1;
	#1
	test_ok = 1'b0;
	#1
	test_ok = 1'b1;
	#1
	test_ok = 1'b0;
	#1
	test_ok = 1'b1;
	#1
	test_ok = 1'b0;
	#1
	
	$finish;
end

endmodule

divisor_4b_tb.vcd
$date
	Wed Jun 07 19:08:23 2023
$end
$version
	Icarus Verilog
$end
$timescale
	1ps
$end
$scope module divisor_4b_tb $end
$var wire 4 ! test_leds [3:0] $end
$var reg 1 " clk $end
$var reg 1 # test_down $end
$var reg 1 $ test_ok $end
$var reg 1 % test_rst $end
$var reg 1 & test_up $end
$scope module UUT $end
$var wire 1 " clk $end
$var wire 4 ' den [3:0] $end
$var wire 1 # down $end
$var wire 4 ( num [3:0] $end
$var wire 1 $ ok $end
$var wire 4 ) rest [3:0] $end
$var wire 4 * result [3:0] $end
$var wire 1 % rst $end
$var wire 1 & up $end
$var wire 2 + sel [1:0] $end
$var wire 4 , leds [3:0] $end
$scope module contador_2b_0 $end
$var wire 1 " clk $end
$var wire 1 % rst $end
$var wire 1 $ up $end
$var reg 2 - curr_numero [1:0] $end
$var reg 1 . enable_up $end
$var reg 2 / next_numero [1:0] $end
$upscope $end
$scope module mux_4b_4_1_a_leds $end
$var wire 4 0 d0 [3:0] $end
$var wire 4 1 d1 [3:0] $end
$var wire 4 2 d2 [3:0] $end
$var wire 4 3 d3 [3:0] $end
$var wire 2 4 sel [1:0] $end
$var reg 4 5 f [3:0] $end
$upscope $end
$upscope $end
$upscope $end
$enddefinitions $end
#0
$dumpvars
bx 5
bx 4
b1000 3
b100 2
b10 1
b1 0
bx /
1.
bx -
bx ,
bx +
b100 *
b1000 )
b1 (
b10 '
x&
1%
x$
x#
0"
bx !
$end
#50000
b0 /
b1 !
b1 ,
b1 5
b0 +
b0 -
b0 4
1"
#100000
0"
0%
#150000
1"
#200000
0"
#250000
1"
#300000
0"
#350000
1"
#400000
0"
#450000
1"
#500000
0"
#550000
1"
#600000
b1 /
0"
1$
#650000
b10 /
b10 !
b10 ,
b10 5
0.
b1 +
b1 -
b1 4
1"
#700000
b1 /
0"
0$
#750000
1.
1"
#800000
b10 /
0"
1$
#850000
b11 /
b100 !
b100 ,
b100 5
0.
b10 +
b10 -
b10 4
1"
#900000
b10 /
0"
0$
#950000
1.
1"
#1000000
b11 /
0"
1$
#1050000
b0 /
b1000 !
b1000 ,
b1000 5
0.
b11 +
b11 -
b11 4
1"
#1100000
b11 /
0"
0$
#1150000
1.
1"
#1200000
b0 /
0"
1$
#1250000
b1 /
b1 !
b1 ,
b1 5
0.
b0 +
b0 -
b0 4
1"
#1300000
b0 /
0"
0$
#1350000
1.
1"
#1400000
b1 /
0"
1$
#1450000
b10 /
b10 !
b10 ,
b10 5
0.
b1 +
b1 -
b1 4
1"
#1500000
b1 /
0"
0$
#1550000
1.
1"
