demux_4b_1_4/demux_4b_1_4.v
module demux_4b_1_4(
	input wire [1:0] sel,
	input wire [3:0] d,
	output reg [3:0] y0, y1, y2, y3
);
always @(sel or d)
	case (sel)
		2'b00 : y0 = d;
		2'b01 : y1 = d;
		2'b10 : y2 = d;
		2'b11 : y3 = d;
	endcase
endmodule

divisor/divisor.v
module divisor(
	input wire clk, rst,
	input wire [3:0] A,
	input wire [3:0] B,
	output reg [3:0] S,
	output reg [3:0] R
);
	
	
localparam [1:0] 
	espera = 2'b00,
	error = 2'b01,
	resta = 2'b10,
	fin = 2'b11;
	
reg [1:0] state, next_state;
reg [3:0] A_reg, next_A, iteracion;


always @(posedge clk)
	begin	
		if(rst)
			begin 
				state <= espera;
			end
		else
			begin
				A_reg <= next_A;
				state <= next_state;
			end
	end


always @*
	case(state)
		espera :
			begin
				if(A < B | B == 0) 
					next_state <= error;
				else 
					next_state <= resta;
					next_A <= A;
					iteracion <= 0;
			end
		 resta :		
			if(A_reg < B)
				next_state <= fin;
			else
				begin
					next_state <= resta;
					next_A <= A_reg-B;
					iteracion++;
				end
		fin :
			begin
				next_state <= fin;
				next_A <= R;
				S <= iteracion;
				R <= A_reg;
			end
	endcase
endmodule

mux_4b_4_1/mux_4b_4_1.v
module mux_4b_4_1(
	input wire [1:0] sel,
	input wire [3:0] d3, d2, d1, d0,
	output reg [3:0] f
);

	always @(d3 or d2 or d1 or d0 or sel)
		case (sel)
			2'b00 : f = d0;
			2'b01 : f = d1;
			2'b10 : f = d2;
			2'b11 : f = d3;
		endcase
	
endmodule

contador_2b/contador_2b.v
module contador_2b(
	input wire clk, up,
	input rst,
	output reg [1:0] curr_numero
);

reg [1:0] next_numero;
localparam [1:0] 	b0 = 2'b00,
					b1 = 2'b01,
					b2 = 2'b10,
					b3 = 2'b11;

reg enable_up = 1; // enable para cuando se suelta el boton 


always @(posedge clk) begin

	if (rst) curr_numero <= b0;

	if(up) begin
		if(enable_up)
			begin
				curr_numero <= next_numero;
				enable_up <= 0;
			end
	end else
		enable_up <= 1;
end

always @*
	case ({up,curr_numero})
	 //contando hacia arriba
		{1'b1,b0} : next_numero = b1;
		{1'b1,b1} : next_numero = b2;
		{1'b1,b2} : next_numero = b3;
		{1'b1,b3} : next_numero = b0;
		default : next_numero = curr_numero;
	
	endcase



endmodule

contador_4b/contador_4b.v
module contador_4b(
	input wire clk, up, down, enable,
	input rst,
	output reg [3:0] curr_numero
);

reg [3:0] next_numero;

reg enable_btn = 1;

localparam [3:0] 	b00 = 4'b0000,
					b01 = 4'b0001,
					b02 = 4'b0010,
					b03 = 4'b0011,
					b04 = 4'b0100,
					b05 = 4'b0101,
					b06 = 4'b0110,
					b07 = 4'b0111,
					b08 = 4'b1000,
					b09 = 4'b1001,
					b10 = 4'b1010,
					b11 = 4'b1011,
					b12 = 4'b1100,
					b13 = 4'b1101,
					b14 = 4'b1110,
					b15 = 4'b1111;

always @(posedge clk)
	begin
		if (rst) curr_numero <= b00;
		else
		if(up ^ down) begin
			if(enable_btn & enable)
				begin
					curr_numero <= next_numero;
					enable_btn <= 0;
				end
		end else
			enable_btn <=1;
	end

always @*
	case ({down,up,curr_numero})
	 //contando hacia arriba
		{1'b0,1'b1,b00} : next_numero = b01;
		{1'b0,1'b1,b01} : next_numero = b02;
		{1'b0,1'b1,b02} : next_numero = b03;
		{1'b0,1'b1,b03} : next_numero = b04;
		{1'b0,1'b1,b04} : next_numero = b05;
		{1'b0,1'b1,b05} : next_numero = b06;
		{1'b0,1'b1,b06} : next_numero = b07;
		{1'b0,1'b1,b07} : next_numero = b08;
		{1'b0,1'b1,b08} : next_numero = b09;
		{1'b0,1'b1,b09} : next_numero = b10;
		{1'b0,1'b1,b10} : next_numero = b11;
		{1'b0,1'b1,b11} : next_numero = b12;
		{1'b0,1'b1,b12} : next_numero = b13;
		{1'b0,1'b1,b13} : next_numero = b14;
		{1'b0,1'b1,b14} : next_numero = b15;
		{1'b0,1'b1,b15} : next_numero = b00;
	//contando hacia abajo
		{1'b1,1'b0,b00} : next_numero = b15;
		{1'b1,1'b0,b01} : next_numero = b00;
		{1'b1,1'b0,b02} : next_numero = b01;
		{1'b1,1'b0,b03} : next_numero = b02;
		{1'b1,1'b0,b04} : next_numero = b03;
		{1'b1,1'b0,b05} : next_numero = b04;
		{1'b1,1'b0,b06} : next_numero = b05;
		{1'b1,1'b0,b07} : next_numero = b06;
		{1'b1,1'b0,b08} : next_numero = b07;
		{1'b1,1'b0,b09} : next_numero = b08;
		{1'b1,1'b0,b10} : next_numero = b09;
		{1'b1,1'b0,b11} : next_numero = b10;
		{1'b1,1'b0,b12} : next_numero = b11;
		{1'b1,1'b0,b13} : next_numero = b12;
		{1'b1,1'b0,b14} : next_numero = b13;
		{1'b1,1'b0,b15} : next_numero = b14;
		default : next_numero = curr_numero;
	
	endcase



endmodule

divisor_4b.v
`include "mux_4b_4_1/mux_4b_4_1.v"
`include "contador_2b/contador_2b.v"
`include "demux_4b_1_4/demux_4b_1_4.v"
`include "contador_4b/contador_4b.v"
`include "divisor/divisor.v"

module divisor_4b(
	input wire up, down, ok, clk, rst,
	output wire [3:0] leds
	);


wire[3:0] num, den;
wire[3:0] result, rest;
wire [1:0] sel;
wire [3:0] numero_4b;

wire up_inv, down_inv, ok_inv, rst_inv;

assign up_inv = ~up;
assign down_inv = ~down;
assign rst_inv = ~rst;
assign ok_inv = ~ok;

//para probar
//assign result = 4'b0111;
//assign rest = 4'b1000;
//fin para probar

wire rst_contador_4b = ok_inv | rst_inv;
wire enable_cont_num = (sel == 2'b00);
wire enable_cont_den = (sel == 2'b01);

contador_4b contador_4b_num(
	.enable(enable_cont_num),
	.clk(clk),
	.up(up_inv),
	.down(down_inv),
	.rst(rst_inv),
	.curr_numero(num)
);
contador_4b contador_4b_den(
	.enable(enable_cont_den),
	.clk(clk),
	.up(up_inv),
	.down(down_inv),
	.rst(rst_inv),
	.curr_numero(den)
);

// demux_4b_1_4 demux_4b_1_4_0(
	// .sel(sel),
	// .d(numero_4b),
	// .y0(num),
	// .y1(den)
// );


contador_2b contador_2b_0(
	.clk(clk),
	.up(ok_inv),
	.rst(rst_inv),
	.curr_numero(sel)
);

mux_4b_4_1 mux_4b_4_1_a_leds(
	.d0(num),
	.d1(den),
	.d2(result),
	.d3(rest),
	.f(leds),
	.sel(sel)
);

wire rst_div = (sel[1] == 0);
divisor divisor0(
	//.rst(rst_div),
	.clk(clk),
	.A(num),
	.B(den),
	.S(result),
	.R(rest)
);
endmodule

divisor_4b_tb.v
`default_nettype none
`define DUMPSTR(x) `"x.vcd`"
`timescale 100 ns / 10 ns

module divisor_4b_tb();

reg clk = 0;
always #0.5 clk = ~clk; //cada 0.5 unidades temporales se niega el clk

reg test_rst, test_down, test_up, test_ok;
wire [3:0] test_leds;

divisor_4b UUT (//-- Instantiate the unit to test
	.clk(clk),
	.rst(test_rst),
	.down(test_down),
	.up(test_up),
	.ok(test_ok),
	.leds(test_leds)
);


initial begin
	$dumpfile(`DUMPSTR(`VCD_OUTPUT));//-- File were to store the simulation results
	$dumpvars(0, divisor_4b_tb);
	
	
	test_rst=1'b1;
	#1
	test_rst=1'b0;
	#1
	test_up = 1;
	test_down = 0;
	#1
	test_up = 0;
	#1
	test_up = 1;
	#1
	test_up = 0;
	#1
	test_up = 1;
	#1
	test_up = 0;
	#1
	test_up = 1;
	#1
	test_up = 0;
	#5
	test_ok = 1'b1;
	#1
	test_ok = 1'b0;
	#1
	//cargo denominador
	test_up = 1;
	#1
	test_up = 0;
	#1
	test_up = 1;
	#1
	test_up = 0;
	#1
	test_up = 1;
	#1
	test_up = 0;
	#1
	test_up = 1;
	#1
	test_up = 0;
	#1
	test_up = 1;
	#1
	test_up = 0;
	#1
	test_down = 1;
	#1
	test_down = 0;
	#10
	test_ok = 1'b1;
	#1
	test_ok = 1'b0;
	#10
	
	
	test_ok = 1'b1;
	#1
	test_ok = 1'b0;
	
	#1
	test_ok = 1'b1;
	#1
	test_ok = 1'b0;
	#1
	test_ok = 1'b1;
	#1
	test_ok = 1'b0;
	#1
	test_ok = 1'b1;
	#1
	test_ok = 1'b0;
	#1
	test_ok = 1'b1;
	#1
	test_ok = 1'b0;
	#1
	test_ok = 1'b1;
	#1
	test_ok = 1'b0;
	#1
	
	$finish;
end

endmodule

divisor_4b_tb.vcd
$date
	Fri Jun 16 11:55:42 2023
$end
$version
	Icarus Verilog
$end
$timescale
	1ps
$end
$scope module divisor_4b_tb $end
$var wire 4 ! test_leds [3:0] $end
$var reg 1 " clk $end
$var reg 1 # test_down $end
$var reg 1 $ test_ok $end
$var reg 1 % test_rst $end
$var reg 1 & test_up $end
$scope module UUT $end
$var wire 1 " clk $end
$var wire 1 # down $end
$var wire 1 ' down_inv $end
$var wire 1 $ ok $end
$var wire 1 ( ok_inv $end
$var wire 1 % rst $end
$var wire 1 ) rst_contador_4b $end
$var wire 1 * rst_inv $end
$var wire 1 & up $end
$var wire 1 + up_inv $end
$var wire 2 , sel [1:0] $end
$var wire 1 - rst_div $end
$var wire 4 . result [3:0] $end
$var wire 4 / rest [3:0] $end
$var wire 4 0 num [3:0] $end
$var wire 4 1 leds [3:0] $end
$var wire 1 2 enable_cont_num $end
$var wire 1 3 enable_cont_den $end
$var wire 4 4 den [3:0] $end
$scope module contador_2b_0 $end
$var wire 1 " clk $end
$var wire 1 * rst $end
$var wire 1 ( up $end
$var reg 2 5 curr_numero [1:0] $end
$var reg 1 6 enable_up $end
$var reg 2 7 next_numero [1:0] $end
$upscope $end
$scope module contador_4b_den $end
$var wire 1 " clk $end
$var wire 1 ' down $end
$var wire 1 3 enable $end
$var wire 1 * rst $end
$var wire 1 + up $end
$var reg 4 8 curr_numero [3:0] $end
$var reg 1 9 enable_btn $end
$var reg 4 : next_numero [3:0] $end
$upscope $end
$scope module contador_4b_num $end
$var wire 1 " clk $end
$var wire 1 ' down $end
$var wire 1 2 enable $end
$var wire 1 * rst $end
$var wire 1 + up $end
$var reg 4 ; curr_numero [3:0] $end
$var reg 1 < enable_btn $end
$var reg 4 = next_numero [3:0] $end
$upscope $end
$scope module divisor0 $end
$var wire 4 > A [3:0] $end
$var wire 4 ? B [3:0] $end
$var wire 1 " clk $end
$var wire 1 - rst $end
$var reg 4 @ A_reg [3:0] $end
$var reg 4 A R [3:0] $end
$var reg 4 B S [3:0] $end
$var reg 4 C iteracion [3:0] $end
$var reg 4 D next_A [3:0] $end
$var reg 2 E next_state [1:0] $end
$var reg 2 F state [1:0] $end
$upscope $end
$scope module mux_4b_4_1_a_leds $end
$var wire 4 G d0 [3:0] $end
$var wire 4 H d1 [3:0] $end
$var wire 4 I d2 [3:0] $end
$var wire 4 J d3 [3:0] $end
$var wire 2 K sel [1:0] $end
$var reg 4 L f [3:0] $end
$upscope $end
$upscope $end
$upscope $end
$enddefinitions $end
#0
$dumpvars
bx L
bx K
bx J
bx I
bx H
bx G
bx F
bx E
bx D
bx C
bx B
bx A
bx @
bx ?
bx >
bx =
1<
bx ;
bx :
19
bx 8
bx 7
16
bx 5
bx 4
x3
x2
bx 1
bx 0
bx /
bx .
x-
bx ,
x+
1*
1)
x(
x'
x&
1%
x$
x#
0"
bx !
$end
#50000
b0 =
b0 :
b0 7
b0 !
b0 1
b0 L
1-
b0 0
b0 ;
b0 >
b0 G
b0 4
b0 8
b0 ?
b0 H
03
12
b0 ,
b0 5
b0 K
1"
#100000
x)
0"
0*
0%
#150000
b0 C
b0 D
b1 E
b0 F
1"
#200000
b1 :
b1 =
0"
0'
0#
1+
1&
#250000
b1 D
b10 =
b1 !
b1 1
b1 L
0<
b1 0
b1 ;
b1 >
b1 G
1"
#300000
b0 :
b1 =
0"
0+
0&
#350000
1<
1"
#400000
b1 :
b10 =
0"
1+
1&
#450000
b10 D
b11 =
b10 !
b10 1
b10 L
0<
b10 0
b10 ;
b10 >
b10 G
1"
#500000
b0 :
b10 =
0"
0+
0&
#550000
1<
1"
#600000
b1 :
b11 =
0"
1+
1&
#650000
b11 D
b100 =
b11 !
b11 1
b11 L
0<
b11 0
b11 ;
b11 >
b11 G
1"
#700000
b0 :
b11 =
0"
0+
0&
#750000
1<
1"
#800000
b1 :
b100 =
0"
1+
1&
#850000
b100 D
b101 =
b100 !
b100 1
b100 L
0<
b100 0
b100 ;
b100 >
b100 G
1"
#900000
b0 :
b100 =
0"
0+
0&
#950000
1<
1"
#1000000
0"
#1050000
1"
#1100000
0"
#1150000
1"
#1200000
0"
#1250000
1"
#1300000
0"
#1350000
1"
#1400000
1)
b1 7
0"
1(
1$
#1450000
b10 7
b0 !
b0 1
b0 L
06
13
02
b1 ,
b1 5
b1 K
1"
#1500000
0)
b1 7
0"
0(
0$
#1550000
16
1"
#1600000
b1 :
b101 =
0"
1+
1&
#1650000
b10 E
b10 :
b1 !
b1 1
b1 L
09
b1 4
b1 8
b1 ?
b1 H
1"
#1700000
b1 :
b100 =
0"
0+
0&
#1750000
19
1"
#1800000
b10 :
b101 =
0"
1+
1&
#1850000
b11 :
b10 !
b10 1
b10 L
09
b10 4
b10 8
b10 ?
b10 H
1"
#1900000
b10 :
b100 =
0"
0+
0&
#1950000
19
1"
#2000000
b11 :
b101 =
0"
1+
1&
#2050000
b100 :
b11 !
b11 1
b11 L
09
b11 4
b11 8
b11 ?
b11 H
1"
#2100000
b11 :
b100 =
0"
0+
0&
#2150000
19
1"
#2200000
b100 :
b101 =
0"
1+
1&
#2250000
b101 :
b100 !
b100 1
b100 L
09
b100 4
b100 8
b100 ?
b100 H
1"
#2300000
b100 :
b100 =
0"
0+
0&
#2350000
19
1"
#2400000
b101 :
b101 =
0"
1+
1&
#2450000
b1 E
b110 :
b101 !
b101 1
b101 L
09
b101 4
b101 8
b101 ?
b101 H
1"
#2500000
b101 :
b100 =
0"
0+
0&
#2550000
19
1"
#2600000
b100 :
b11 =
0"
1'
1#
#2650000
b10 E
b11 :
b100 !
b100 1
b100 L
09
b100 4
b100 8
b100 ?
b100 H
1"
#2700000
b100 :
b100 =
0"
0'
0#
#2750000
19
1"
#2800000
0"
#2850000
1"
#2900000
0"
#2950000
1"
#3000000
0"
#3050000
1"
#3100000
0"
#3150000
1"
#3200000
0"
#3250000
1"
#3300000
0"
#3350000
1"
#3400000
0"
#3450000
1"
#3500000
0"
#3550000
1"
#3600000
0"
#3650000
1"
#3700000
1)
b10 7
0"
1(
1$
#3750000
b11 7
bx !
bx 1
bx L
0-
06
03
b10 ,
b10 5
b10 K
1"
#3800000
0)
b10 7
0"
0(
0$
#3850000
b0 D
b1 C
16
b10 F
b100 @
1"
#3900000
0"
#3950000
b11 E
b0 @
1"
#4000000
0"
#4050000
b1 !
b1 1
b1 L
b0 /
b0 A
b0 J
b1 .
b1 B
b1 I
b0 D
b11 F
1"
#4100000
0"
#4150000
1"
#4200000
0"
#4250000
1"
#4300000
0"
#4350000
1"
#4400000
0"
#4450000
1"
#4500000
0"
#4550000
1"
#4600000
0"
#4650000
1"
#4700000
0"
#4750000
1"
#4800000
1)
b11 7
0"
1(
1$
#4850000
b0 7
b0 !
b0 1
b0 L
06
b11 ,
b11 5
b11 K
1"
#4900000
0)
b11 7
0"
0(
0$
#4950000
16
1"
#5000000
1)
b0 7
0"
1(
1$
#5050000
b1 7
b100 !
b100 1
b100 L
1-
06
12
b0 ,
b0 5
b0 K
1"
#5100000
0)
b0 7
0"
0(
0$
#5150000
b0 C
b100 D
b10 E
b0 F
16
1"
#5200000
1)
b1 7
0"
1(
1$
#5250000
b10 7
06
13
02
b1 ,
b1 5
b1 K
1"
#5300000
0)
b1 7
0"
0(
0$
#5350000
16
1"
#5400000
1)
b10 7
0"
1(
1$
#5450000
b11 7
b1 !
b1 1
b1 L
0-
06
03
b10 ,
b10 5
b10 K
1"
#5500000
0)
b10 7
0"
0(
0$
#5550000
b0 D
b1 C
b10 F
b100 @
16
1"
#5600000
1)
b11 7
0"
1(
1$
#5650000
b11 E
b0 7
b0 !
b0 1
b0 L
06
b11 ,
b11 5
b11 K
b0 @
1"
#5700000
0)
b11 7
0"
0(
0$
#5750000
b11 F
16
1"
#5800000
1)
b0 7
0"
1(
1$
#5850000
b1 7
b100 !
b100 1
b100 L
1-
06
12
b0 ,
b0 5
b0 K
1"
#5900000
0)
b0 7
0"
0(
0$
#5950000
b0 C
b100 D
b10 E
b0 F
16
1"
