mux_4b_4_1/mux_4b_4_1.v
module mux_4b_4_1(
	input wire [1:0] sel,
	input wire [3:0] d3, d2, d1, d0,
	output reg [3:0] f
);

	always @(d3 or d2 or d1 or d0 or sel)
		case (sel)
			2'b00 : f = d0;
			2'b01 : f = d1;
			2'b10 : f = d2;
			2'b11 : f = d3;
		endcase
	
endmodule

contador_2b/contador_2b.v
module contador_2b(
	input wire clk, up,
	input rst,
	output reg [1:0] curr_numero
);

reg [1:0] next_numero;
localparam [1:0] 	b0 = 2'b00,
					b1 = 2'b01,
					b2 = 2'b10,
					b3 = 2'b11;

reg enable_up = 1; // enable para cuando se suelta el boton 


always @(posedge clk) begin

	if (rst) curr_numero <= b0;

	if(up) begin
		if(enable_up)
			begin
				curr_numero <= next_numero;
				enable_up <= 0;
			end
	end else
		enable_up <= 1;
end

always @*
	case ({up,curr_numero})
	 //contando hacia arriba
		{1'b1,b0} : next_numero = b1;
		{1'b1,b1} : next_numero = b2;
		{1'b1,b2} : next_numero = b3;
		{1'b1,b3} : next_numero = b0;
		default : next_numero = curr_numero;
	
	endcase



endmodule

demux_4b_1_4/demux_4b_1_4.v
module demux_4b_1_4(
	input wire [1:0] sel,
	input wire [3:0] d,
	output reg [3:0] y0, y1, y2, y3
);
always @(sel or d)
	case (sel)
		2'b00 : y0 = d;
		2'b01 : y1 = d;
		2'b10 : y2 = d;
		2'b11 : y3 = d;
	endcase
endmodule

contador_4b/contador_4b.v
module contador_4b(
	input wire clk, up, down,
	input rst,
	output reg [3:0] curr_numero
);

reg [3:0] next_numero;

reg enable_btn = 1;

localparam [3:0] 	b00 = 4'b0000,
					b01 = 4'b0001,
					b02 = 4'b0010,
					b03 = 4'b0011,
					b04 = 4'b0100,
					b05 = 4'b0101,
					b06 = 4'b0110,
					b07 = 4'b0111,
					b08 = 4'b1000,
					b09 = 4'b1001,
					b10 = 4'b1010,
					b11 = 4'b1011,
					b12 = 4'b1100,
					b13 = 4'b1101,
					b14 = 4'b1110,
					b15 = 4'b1111;

always @(posedge clk)
	begin
		if (rst) curr_numero <= b00;
		else
		if(up ^ down) begin
			if(enable_btn)
				begin
					curr_numero <= next_numero;
					enable_btn <= 0;
				end
		end else
			enable_btn <=1;
	end

always @*
	case ({down,up,curr_numero})
	 //contando hacia arriba
		{1'b0,1'b1,b00} : next_numero = b01;
		{1'b0,1'b1,b01} : next_numero = b02;
		{1'b0,1'b1,b02} : next_numero = b03;
		{1'b0,1'b1,b03} : next_numero = b04;
		{1'b0,1'b1,b04} : next_numero = b05;
		{1'b0,1'b1,b05} : next_numero = b06;
		{1'b0,1'b1,b06} : next_numero = b07;
		{1'b0,1'b1,b07} : next_numero = b08;
		{1'b0,1'b1,b08} : next_numero = b09;
		{1'b0,1'b1,b09} : next_numero = b10;
		{1'b0,1'b1,b10} : next_numero = b11;
		{1'b0,1'b1,b11} : next_numero = b12;
		{1'b0,1'b1,b12} : next_numero = b13;
		{1'b0,1'b1,b13} : next_numero = b14;
		{1'b0,1'b1,b14} : next_numero = b15;
		{1'b0,1'b1,b15} : next_numero = b00;
	//contando hacia abajo
		{1'b1,1'b0,b00} : next_numero = b15;
		{1'b1,1'b0,b01} : next_numero = b00;
		{1'b1,1'b0,b02} : next_numero = b01;
		{1'b1,1'b0,b03} : next_numero = b02;
		{1'b1,1'b0,b04} : next_numero = b03;
		{1'b1,1'b0,b05} : next_numero = b04;
		{1'b1,1'b0,b06} : next_numero = b05;
		{1'b1,1'b0,b07} : next_numero = b06;
		{1'b1,1'b0,b08} : next_numero = b07;
		{1'b1,1'b0,b09} : next_numero = b08;
		{1'b1,1'b0,b10} : next_numero = b09;
		{1'b1,1'b0,b11} : next_numero = b10;
		{1'b1,1'b0,b12} : next_numero = b11;
		{1'b1,1'b0,b13} : next_numero = b12;
		{1'b1,1'b0,b14} : next_numero = b13;
		{1'b1,1'b0,b15} : next_numero = b14;
		default : next_numero = curr_numero;
	
	endcase



endmodule

divisor_4b.v
`include "mux_4b_4_1/mux_4b_4_1.v"
`include "contador_2b/contador_2b.v"
`include "demux_4b_1_4/demux_4b_1_4.v"
`include "contador_4b/contador_4b.v"

module divisor_4b(
	input wire up, down, ok, clk, rst,
	output wire [3:0] leds
	);


wire[3:0] num, den;
wire[3:0] result, rest;
wire [1:0] sel;
wire [3:0] numero_4b;

//para probar
assign result = 4'b0111;
assign rest = 4'b1000;
//fin para probar

wire rst_contador_4b = ok | rst;

contador_4b contador_4b_0(
	.clk(clk),
	.up(up),
	.down(down),
	.rst(rst_contador_4b),
	.curr_numero(numero_4b)
);

demux_4b_1_4 demux_4b_1_4_0(
	.sel(sel),
	.d(numero_4b),
	.y0(num),
	.y1(den)
);


contador_2b contador_2b_0(
	.clk(clk),
	.up(ok),
	.rst(rst),
	.curr_numero(sel)
);

mux_4b_4_1 mux_4b_4_1_a_leds(
	.d0(num),
	.d1(den),
	.d2(result),
	.d3(rest),
	.f(leds),
	.sel(sel)
);

endmodule

divisor_4b_tb.v
`default_nettype none
`define DUMPSTR(x) `"x.vcd`"
`timescale 100 ns / 10 ns

module divisor_4b_tb();

reg clk = 0;
always #0.5 clk = ~clk; //cada 0.5 unidades temporales se niega el clk

reg test_rst, test_down, test_up, test_ok;
wire [3:0] test_leds;

divisor_4b UUT (//-- Instantiate the unit to test
	.clk(clk),
	.rst(test_rst),
	.down(test_down),
	.up(test_up),
	.ok(test_ok),
	.leds(test_leds)
);


initial begin
	$dumpfile(`DUMPSTR(`VCD_OUTPUT));//-- File were to store the simulation results
	$dumpvars(0, divisor_4b_tb);
	
	
	test_rst=1'b1;
	#1
	test_rst=1'b0;
	#1
	test_up = 1;
	test_down = 0;
	#1
	test_up = 0;
	#1
	test_up = 1;
	#1
	test_up = 0;
	#1
	test_up = 1;
	#1
	test_up = 0;
	#1
	test_up = 1;
	#1
	test_up = 0;
	#5
	test_ok = 1'b1;
	#1
	test_ok = 1'b0;
	#1
	//cargo denominador
	test_up = 1;
	#1
	test_up = 0;
	#1
	test_up = 1;
	#1
	test_up = 0;
	#1
	test_up = 1;
	#1
	test_up = 0;
	#1
	test_up = 1;
	#1
	test_up = 0;
	#1
	test_up = 1;
	#1
	test_up = 0;
	#1
	test_down = 1;
	#1
	test_down = 0;
	#1
	test_ok = 1'b1;
	#1
	test_ok = 1'b0;
	#1
	test_ok = 1'b1;
	#1
	test_ok = 1'b0;
	#1
	test_rst = 1;
	#1
	test_rst = 0;
	#1
	test_ok = 1'b1;
	#1
	test_ok = 1'b0;
	#3
	
	$finish;
end

endmodule

divisor_4b_tb.vcd
$date
	Thu Jun 08 17:10:26 2023
$end
$version
	Icarus Verilog
$end
$timescale
	1ps
$end
$scope module divisor_4b_tb $end
$var wire 4 ! test_leds [3:0] $end
$var reg 1 " clk $end
$var reg 1 # test_down $end
$var reg 1 $ test_ok $end
$var reg 1 % test_rst $end
$var reg 1 & test_up $end
$scope module UUT $end
$var wire 1 " clk $end
$var wire 1 # down $end
$var wire 1 $ ok $end
$var wire 4 ' rest [3:0] $end
$var wire 4 ( result [3:0] $end
$var wire 1 % rst $end
$var wire 1 ) rst_contador_4b $end
$var wire 1 & up $end
$var wire 2 * sel [1:0] $end
$var wire 4 + numero_4b [3:0] $end
$var wire 4 , num [3:0] $end
$var wire 4 - leds [3:0] $end
$var wire 4 . den [3:0] $end
$scope module contador_2b_0 $end
$var wire 1 " clk $end
$var wire 1 % rst $end
$var wire 1 $ up $end
$var reg 2 / curr_numero [1:0] $end
$var reg 1 0 enable_up $end
$var reg 2 1 next_numero [1:0] $end
$upscope $end
$scope module contador_4b_0 $end
$var wire 1 " clk $end
$var wire 1 # down $end
$var wire 1 ) rst $end
$var wire 1 & up $end
$var reg 4 2 curr_numero [3:0] $end
$var reg 1 3 enable_btn $end
$var reg 4 4 next_numero [3:0] $end
$upscope $end
$scope module demux_4b_1_4_0 $end
$var wire 4 5 d [3:0] $end
$var wire 2 6 sel [1:0] $end
$var reg 4 7 y0 [3:0] $end
$var reg 4 8 y1 [3:0] $end
$var reg 4 9 y2 [3:0] $end
$var reg 4 : y3 [3:0] $end
$upscope $end
$scope module mux_4b_4_1_a_leds $end
$var wire 4 ; d0 [3:0] $end
$var wire 4 < d1 [3:0] $end
$var wire 4 = d2 [3:0] $end
$var wire 4 > d3 [3:0] $end
$var wire 2 ? sel [1:0] $end
$var reg 4 @ f [3:0] $end
$upscope $end
$upscope $end
$upscope $end
$enddefinitions $end
#0
$dumpvars
bx @
bx ?
b1000 >
b111 =
bx <
bx ;
bx :
bx 9
bx 8
bx 7
bx 6
bx 5
bx 4
13
bx 2
bx 1
10
bx /
bx .
bx -
bx ,
bx +
bx *
1)
b111 (
b1000 '
x&
1%
x$
x#
0"
bx !
$end
#50000
b0 !
b0 -
b0 @
b0 4
b0 1
b0 ,
b0 7
b0 ;
b0 +
b0 2
b0 5
b0 *
b0 /
b0 6
b0 ?
1"
#100000
x)
0"
0%
#150000
1"
#200000
b1 4
0"
0#
1&
#250000
b1 !
b1 -
b1 @
b10 4
b1 ,
b1 7
b1 ;
03
b1 +
b1 2
b1 5
1"
#300000
b1 4
0"
0&
#350000
13
1"
#400000
b10 4
0"
1&
#450000
b10 !
b10 -
b10 @
b11 4
b10 ,
b10 7
b10 ;
03
b10 +
b10 2
b10 5
1"
#500000
b10 4
0"
0&
#550000
13
1"
#600000
b11 4
0"
1&
#650000
b11 !
b11 -
b11 @
b100 4
b11 ,
b11 7
b11 ;
03
b11 +
b11 2
b11 5
1"
#700000
b11 4
0"
0&
#750000
13
1"
#800000
b100 4
0"
1&
#850000
b100 !
b100 -
b100 @
b101 4
b100 ,
b100 7
b100 ;
03
b100 +
b100 2
b100 5
1"
#900000
b100 4
0"
0&
#950000
13
1"
#1000000
0"
#1050000
1"
#1100000
0"
#1150000
1"
#1200000
0"
#1250000
1"
#1300000
0"
#1350000
1"
#1400000
1)
b1 1
0"
1$
#1450000
b0 4
b10 1
b0 .
b0 8
b0 <
b0 !
b0 -
b0 @
b0 +
b0 2
b0 5
00
b1 *
b1 /
b1 6
b1 ?
1"
#1500000
0)
b1 1
0"
0$
#1550000
10
1"
#1600000
b1 4
0"
1&
#1650000
b1 !
b1 -
b1 @
b10 4
b1 .
b1 8
b1 <
03
b1 +
b1 2
b1 5
1"
#1700000
b1 4
0"
0&
#1750000
13
1"
#1800000
b10 4
0"
1&
#1850000
b10 !
b10 -
b10 @
b11 4
b10 .
b10 8
b10 <
03
b10 +
b10 2
b10 5
1"
#1900000
b10 4
0"
0&
#1950000
13
1"
#2000000
b11 4
0"
1&
#2050000
b11 !
b11 -
b11 @
b100 4
b11 .
b11 8
b11 <
03
b11 +
b11 2
b11 5
1"
#2100000
b11 4
0"
0&
#2150000
13
1"
#2200000
b100 4
0"
1&
#2250000
b100 !
b100 -
b100 @
b101 4
b100 .
b100 8
b100 <
03
b100 +
b100 2
b100 5
1"
#2300000
b100 4
0"
0&
#2350000
13
1"
#2400000
b101 4
0"
1&
#2450000
b101 !
b101 -
b101 @
b110 4
b101 .
b101 8
b101 <
03
b101 +
b101 2
b101 5
1"
#2500000
b101 4
0"
0&
#2550000
13
1"
#2600000
b100 4
0"
1#
#2650000
b100 !
b100 -
b100 @
b11 4
b100 .
b100 8
b100 <
03
b100 +
b100 2
b100 5
1"
#2700000
b100 4
0"
0#
#2750000
13
1"
#2800000
1)
b10 1
0"
1$
#2850000
b0 4
b11 1
b0 9
b111 !
b111 -
b111 @
b0 +
b0 2
b0 5
00
b10 *
b10 /
b10 6
b10 ?
1"
#2900000
0)
b10 1
0"
0$
#2950000
10
1"
#3000000
1)
b11 1
0"
1$
#3050000
b0 1
b0 :
b1000 !
b1000 -
b1000 @
00
b11 *
b11 /
b11 6
b11 ?
1"
#3100000
0)
b11 1
0"
0$
#3150000
10
1"
#3200000
1)
0"
1%
#3250000
b0 1
b0 ,
b0 7
b0 ;
b0 !
b0 -
b0 @
b0 *
b0 /
b0 6
b0 ?
1"
#3300000
0)
0"
0%
#3350000
1"
#3400000
1)
b1 1
0"
1$
#3450000
b10 1
b0 .
b0 8
b0 <
b0 !
b0 -
b0 @
00
b1 *
b1 /
b1 6
b1 ?
1"
#3500000
0)
b1 1
0"
0$
#3550000
10
1"
