sumaresta/sumaresta.v
module sumaresta(

	input wire [1:0] A,
	input wire [3:0] Q,
	output wire [3:0] D
	);
	
	assign D[3] =
				(~A[1] & ~A[0] & Q[3]) | 
				(Q[3] & Q[1] & ~Q[0]) |
				(Q[3] & Q[2] & ~Q[1]) |
				(A[0] & Q[3] & ~Q[2]) |
				(A[1] & Q[3] & Q[0]) |
				(~A[1] & A[0] & ~Q[3] & Q[2] & Q[1] & Q[0]) |
				(A[1] & ~A[0] & ~Q[3] & ~Q[2] & ~Q[1] & ~Q[0]);
			
	assign D[2] =
				(~A[1] & ~A[0] & Q[2]) | 
				(Q[2] & Q[1] & ~Q[0]) |
				(A[0] & Q[2] & ~Q[1]) |
				(A[1] & Q[2] & Q[0]) |
				(~A[1] & A[0] & ~Q[2] & Q[1] & Q[0]) |
				(A[1] & ~A[0] & ~Q[2] & ~Q[1] & ~Q[0]);
			
	assign D[1] =
				(~A[1] & ~A[0] & Q[1])	| 
				(A[0] & Q[1] & ~Q[0])	|
				(A[1] & Q[1] & Q[0]) |
				(~A[1] & A[0] & ~Q[1] & Q[0]) |
				(A[1] & ~A[0] & ~Q[1] & ~Q[0]) ;
				
	assign D[0] =
				(~A[1] & ~A[0] & Q[0])	| 
				(~A[1] & A[0] & ~Q[0])	|
				(A[1] & ~A[0] & ~Q[0]) |
				(A[1] & A[0] & Q[0]) ;
			
	endmodule

sumaresta/sumaresta_tb.v
`default_nettype none
`define DUMPSTR(x) `"x.vcd`"
`timescale 100 ns / 10 ns 

//timescale <time_unit> / <time_precision>

module sumaresta_tb();

//-- Simulation time: 1us (10 * 100ns)
parameter DURATION = 10;

//-- Clock signal. It is not used in this simulation
reg clk =0;
always #0.5 clk = ~clk;

reg [1:0] test_A_in;
reg [3:0] test_Q_in;
wire [3:0] test_D_out;


//-- Instantiate the unit to test
sumaresta UUT(
			.A(test_A_in),
			.Q(test_Q_in),
			.D(test_D_out)
			);

integer i;

initial begin

//-- File were to store the simulation result
$dumpfile(`DUMPSTR(`VCD_OUTPUT));
$dumpvars(0, sumaresta_tb);

		test_A_in = 2;

	for	(i=0; i<16; i=i+1)
	begin
		$display ("current loop # %0d", i);
		
		#2

		test_Q_in = i;
	end

	#(DURATION) $display("End of Simulation");
	$finish;
	
end

endmodule

sumaresta/sumaresta_tb.vcd
$date
	Thu Jun 08 09:32:46 2023
$end
$version
	Icarus Verilog
$end
$timescale
	1ps
$end
$scope module sumaresta_tb $end
$var wire 4 ! test_D_out [3:0] $end
$var reg 1 " clk $end
$var reg 2 # test_A_in [1:0] $end
$var reg 4 $ test_Q_in [3:0] $end
$var integer 32 % i [31:0] $end
$scope module UUT $end
$var wire 2 & A [1:0] $end
$var wire 4 ' Q [3:0] $end
$var wire 4 ( D [3:0] $end
$upscope $end
$upscope $end
$enddefinitions $end
#0
$dumpvars
bx (
bx '
b10 &
b0 %
bx $
b10 #
0"
bx !
$end
#50000
1"
#100000
0"
#150000
1"
#200000
b1111 !
b1111 (
0"
b1 %
b0 $
b0 '
#250000
1"
#300000
0"
#350000
1"
#400000
b0 !
b0 (
0"
b10 %
b1 $
b1 '
#450000
1"
#500000
0"
#550000
1"
#600000
b1 !
b1 (
0"
b11 %
b10 $
b10 '
#650000
1"
#700000
0"
#750000
1"
#800000
b10 !
b10 (
0"
b100 %
b11 $
b11 '
#850000
1"
#900000
0"
#950000
1"
#1000000
b11 !
b11 (
0"
b101 %
b100 $
b100 '
#1050000
1"
#1100000
0"
#1150000
1"
#1200000
b100 !
b100 (
0"
b110 %
b101 $
b101 '
#1250000
1"
#1300000
0"
#1350000
1"
#1400000
b101 !
b101 (
0"
b111 %
b110 $
b110 '
#1450000
1"
#1500000
0"
#1550000
1"
#1600000
b110 !
b110 (
0"
b1000 %
b111 $
b111 '
#1650000
1"
#1700000
0"
#1750000
1"
#1800000
b111 !
b111 (
0"
b1001 %
b1000 $
b1000 '
#1850000
1"
#1900000
0"
#1950000
1"
#2000000
b1000 !
b1000 (
0"
b1010 %
b1001 $
b1001 '
#2050000
1"
#2100000
0"
#2150000
1"
#2200000
b1001 !
b1001 (
0"
b1011 %
b1010 $
b1010 '
#2250000
1"
#2300000
0"
#2350000
1"
#2400000
b1010 !
b1010 (
0"
b1100 %
b1011 $
b1011 '
#2450000
1"
#2500000
0"
#2550000
1"
#2600000
b1011 !
b1011 (
0"
b1101 %
b1100 $
b1100 '
#2650000
1"
#2700000
0"
#2750000
1"
#2800000
b1100 !
b1100 (
0"
b1110 %
b1101 $
b1101 '
#2850000
1"
#2900000
0"
#2950000
1"
#3000000
b1101 !
b1101 (
0"
b1111 %
b1110 $
b1110 '
#3050000
1"
#3100000
0"
#3150000
1"
#3200000
b1110 !
b1110 (
0"
b10000 %
b1111 $
b1111 '
