flip_flop_d_rst/flip_flop_d_rst.v
module flip_flop_d_rst(
	input wire D, rst,
	input wire clk,
	output reg Q
);

always @(posedge clk or posedge rst) begin
	if(rst) Q <= 1'b0;
	else Q <= D;
end

endmodule

flip_flop_d_rst/flip_flop_d_rst_tb.v
`default_nettype none
`define DUMPSTR(x) `"x.vcd`"
`timescale 100 ns / 10 ns

module flip_flop_d_rst_tb();

parameter DURATION = 10;

reg clk = 0;
always #0.5 clk = ~clk; //cada 0.5 unidades temporales se niega el clk

reg test_D, test_rst;
wire test_Q;

flip_flop_d_rst UUT (//-- Instantiate the unit to test
	.clk(clk),
	.rst(test_rst),
	.D(test_D),
	.Q(test_Q)
);


initial begin
	$dumpfile(`DUMPSTR(`VCD_OUTPUT));//-- File were to store the simulation results
	$dumpvars(0, flip_flop_d_rst_tb);
		
		test_rst = 0;
		#1
		test_D = 0;
		#5
		test_D = 1;
		#2
		test_rst = 1;
		#2
		test_rst = 0;
		#7
		test_D = 0;
	
	#(DURATION);
	$finish;
end

endmodule

flip_flop_d_rst/flip_flop_d_rst_tb.vcd
$date
	Thu Jun 08 12:10:42 2023
$end
$version
	Icarus Verilog
$end
$timescale
	1ps
$end
$scope module flip_flop_d_rst_tb $end
$var wire 1 ! test_Q $end
$var reg 1 " clk $end
$var reg 1 # test_D $end
$var reg 1 $ test_rst $end
$scope module UUT $end
$var wire 1 # D $end
$var wire 1 " clk $end
$var wire 1 $ rst $end
$var reg 1 ! Q $end
$upscope $end
$upscope $end
$enddefinitions $end
#0
$dumpvars
0$
x#
0"
x!
$end
#50000
1"
#100000
0"
0#
#150000
0!
1"
#200000
0"
#250000
1"
#300000
0"
#350000
1"
#400000
0"
#450000
1"
#500000
0"
#550000
1"
#600000
0"
1#
#650000
1!
1"
#700000
0"
#750000
1"
#800000
0!
0"
1$
#850000
1"
#900000
0"
#950000
1"
#1000000
0"
0$
#1050000
1!
1"
#1100000
0"
#1150000
1"
#1200000
0"
#1250000
1"
#1300000
0"
#1350000
1"
#1400000
0"
#1450000
1"
#1500000
0"
#1550000
1"
#1600000
0"
#1650000
1"
#1700000
0"
0#
#1750000
0!
1"
