contador_4b/contador_4b.v
module contador_4b(
	input wire clk, up, down, enable,
	input rst,
	output reg [3:0] curr_numero
);

reg [3:0] next_numero;

reg enable_btn = 1;

localparam [3:0] 	b00 = 4'b0000,
					b01 = 4'b0001,
					b02 = 4'b0010,
					b03 = 4'b0011,
					b04 = 4'b0100,
					b05 = 4'b0101,
					b06 = 4'b0110,
					b07 = 4'b0111,
					b08 = 4'b1000,
					b09 = 4'b1001,
					b10 = 4'b1010,
					b11 = 4'b1011,
					b12 = 4'b1100,
					b13 = 4'b1101,
					b14 = 4'b1110,
					b15 = 4'b1111;

always @(posedge clk)
	begin
		if (rst) curr_numero <= b00;
		else
		if(up ^ down) begin
			if(enable_btn & enable)
				begin
					curr_numero <= next_numero;
					enable_btn <= 0;
				end
		end else
			enable_btn <=1;
	end

always @*
	case ({down,up,curr_numero})
	 //contando hacia arriba
		{1'b0,1'b1,b00} : next_numero = b01;
		{1'b0,1'b1,b01} : next_numero = b02;
		{1'b0,1'b1,b02} : next_numero = b03;
		{1'b0,1'b1,b03} : next_numero = b04;
		{1'b0,1'b1,b04} : next_numero = b05;
		{1'b0,1'b1,b05} : next_numero = b06;
		{1'b0,1'b1,b06} : next_numero = b07;
		{1'b0,1'b1,b07} : next_numero = b08;
		{1'b0,1'b1,b08} : next_numero = b09;
		{1'b0,1'b1,b09} : next_numero = b10;
		{1'b0,1'b1,b10} : next_numero = b11;
		{1'b0,1'b1,b11} : next_numero = b12;
		{1'b0,1'b1,b12} : next_numero = b13;
		{1'b0,1'b1,b13} : next_numero = b14;
		{1'b0,1'b1,b14} : next_numero = b15;
		{1'b0,1'b1,b15} : next_numero = b00;
	//contando hacia abajo
		{1'b1,1'b0,b00} : next_numero = b15;
		{1'b1,1'b0,b01} : next_numero = b00;
		{1'b1,1'b0,b02} : next_numero = b01;
		{1'b1,1'b0,b03} : next_numero = b02;
		{1'b1,1'b0,b04} : next_numero = b03;
		{1'b1,1'b0,b05} : next_numero = b04;
		{1'b1,1'b0,b06} : next_numero = b05;
		{1'b1,1'b0,b07} : next_numero = b06;
		{1'b1,1'b0,b08} : next_numero = b07;
		{1'b1,1'b0,b09} : next_numero = b08;
		{1'b1,1'b0,b10} : next_numero = b09;
		{1'b1,1'b0,b11} : next_numero = b10;
		{1'b1,1'b0,b12} : next_numero = b11;
		{1'b1,1'b0,b13} : next_numero = b12;
		{1'b1,1'b0,b14} : next_numero = b13;
		{1'b1,1'b0,b15} : next_numero = b14;
		default : next_numero = curr_numero;
	
	endcase



endmodule

contador_4b/contador_4b_tb.v
`default_nettype none
`define DUMPSTR(x) `"x.vcd`"
`timescale 100 ns / 10 ns

module contador_4b_tb();

reg clk = 0;
always #0.5 clk = ~clk; //cada 0.5 unidades temporales se niega el clk

reg test_rst, test_down, test_up, test_enable;
wire test_numero;

contador_4b UUT (//-- Instantiate the unit to test
	.clk(clk),
	.rst(test_rst),
	.down(test_down),
	.up(test_up),
	.enable(test_enable)
);


initial begin
	$dumpfile(`DUMPSTR(`VCD_OUTPUT));//-- File were to store the simulation results
	$dumpvars(0, contador_4b_tb);
	test_enable = 1'b1;
	test_up = 1'b0;
	test_down = 1'b0;
	test_rst=1'b1;
	#1
	test_rst=1'b0;
	#1
	test_up = 1'b1;
	test_down =1'b1;
	#2
	test_down = 1'b0;
	#1
	test_up = 1'b1;
	#1
	test_up = 1'b0;
	#1
	test_up = 1'b1;
	#1
	test_up = 1'b0;
	#1
	test_up = 1'b1;
	#1
	test_up = 1'b0;
	#1
	test_up = 1'b1;
	#1
	test_up = 1'b0;
	#1
	test_up = 1'b1;
	#1
	test_up = 1'b0;
	#1
	test_up = 1'b1;
	#1
	test_up = 1'b0;
	#1
	test_up = 1'b1;
	#1
	test_up = 1'b0;
	#1
	test_up = 1'b1;
	#1
	test_up = 1'b0;
	#1
	test_up = 1'b1;
	#1
	test_up = 1'b0;
	#1
	test_up = 1'b1;
	#1
	test_up = 1'b0;
	#1
	test_up = 1'b1;
	#1
	test_up = 1'b0;
	#1
	test_up = 1'b1;
	#1
	test_up = 1'b0;
	#1
	test_up = 1'b1;
	#1
	test_up = 1'b0;
	#1
	test_up = 1'b1;
	#1
	test_up = 1'b0;
	#1
	test_up = 1'b1;
	#1
	test_up = 1'b0;
	#1
	test_up = 1'b1;
	#1
	test_up = 1'b0;
	#5
	test_rst=1'b1;
	#1
	test_rst=1'b0;
	#20
	test_up = 1'b0;
	#1
	test_down = 1'b1;
	#1
	test_down = 1'b0;
	#1
	test_down = 1'b1;
	#1
	test_down = 1'b0;
	#1
	test_down = 1'b1;
	#1
	test_down = 1'b0;
	#1
	test_down = 1'b1;
	#1
	test_down = 1'b0;
	#1
	test_down = 1'b1;
	#1
	test_down = 1'b0;
	#1
	test_down = 1'b1;
	#1
	test_down = 1'b0;
	#1
	test_down = 1'b1;
	#1
	test_down = 1'b0;
	#1
	test_down = 1'b1;
	#1
	test_down = 1'b0;
	#1
	test_down = 1'b1;
	#1
	test_down = 1'b0;
	#22
	test_rst=1'b1;
	#1
	test_rst=1'b0;
	#5
	test_up = 1'b0;
	test_down = 1'b0;
	#10
	test_up = 1'b0;
	test_down = 1'b1;
	#20
	
	$finish;
end

endmodule

contador_4b/contador_4b_tb.vcd
$date
	Thu Jun 22 15:00:29 2023
$end
$version
	Icarus Verilog
$end
$timescale
	1ps
$end
$scope module contador_4b_tb $end
$var reg 1 ! clk $end
$var reg 1 " test_down $end
$var reg 1 # test_enable $end
$var reg 1 $ test_rst $end
$var reg 1 % test_up $end
$scope module UUT $end
$var wire 1 ! clk $end
$var wire 1 " down $end
$var wire 1 # enable $end
$var wire 1 $ rst $end
$var wire 1 % up $end
$var reg 4 & curr_numero [3:0] $end
$var reg 1 ' enable_btn $end
$var reg 4 ( next_numero [3:0] $end
$upscope $end
$upscope $end
$enddefinitions $end
#0
$dumpvars
bx (
1'
bx &
0%
1$
1#
0"
0!
$end
#50000
b0 (
b0 &
1!
#100000
0!
0$
#150000
1!
#200000
0!
1"
1%
#250000
1!
#300000
0!
#350000
1!
#400000
b1 (
0!
0"
#450000
b10 (
0'
b1 &
1!
#500000
0!
#550000
1!
#600000
b1 (
0!
0%
#650000
1'
1!
#700000
b10 (
0!
1%
#750000
b11 (
0'
b10 &
1!
#800000
b10 (
0!
0%
#850000
1'
1!
#900000
b11 (
0!
1%
#950000
b100 (
0'
b11 &
1!
#1000000
b11 (
0!
0%
#1050000
1'
1!
#1100000
b100 (
0!
1%
#1150000
b101 (
0'
b100 &
1!
#1200000
b100 (
0!
0%
#1250000
1'
1!
#1300000
b101 (
0!
1%
#1350000
b110 (
0'
b101 &
1!
#1400000
b101 (
0!
0%
#1450000
1'
1!
#1500000
b110 (
0!
1%
#1550000
b111 (
0'
b110 &
1!
#1600000
b110 (
0!
0%
#1650000
1'
1!
#1700000
b111 (
0!
1%
#1750000
b1000 (
0'
b111 &
1!
#1800000
b111 (
0!
0%
#1850000
1'
1!
#1900000
b1000 (
0!
1%
#1950000
b1001 (
0'
b1000 &
1!
#2000000
b1000 (
0!
0%
#2050000
1'
1!
#2100000
b1001 (
0!
1%
#2150000
b1010 (
0'
b1001 &
1!
#2200000
b1001 (
0!
0%
#2250000
1'
1!
#2300000
b1010 (
0!
1%
#2350000
b1011 (
0'
b1010 &
1!
#2400000
b1010 (
0!
0%
#2450000
1'
1!
#2500000
b1011 (
0!
1%
#2550000
b1100 (
0'
b1011 &
1!
#2600000
b1011 (
0!
0%
#2650000
1'
1!
#2700000
b1100 (
0!
1%
#2750000
b1101 (
0'
b1100 &
1!
#2800000
b1100 (
0!
0%
#2850000
1'
1!
#2900000
b1101 (
0!
1%
#2950000
b1110 (
0'
b1101 &
1!
#3000000
b1101 (
0!
0%
#3050000
1'
1!
#3100000
b1110 (
0!
1%
#3150000
b1111 (
0'
b1110 &
1!
#3200000
b1110 (
0!
0%
#3250000
1'
1!
#3300000
b1111 (
0!
1%
#3350000
b0 (
0'
b1111 &
1!
#3400000
b1111 (
0!
0%
#3450000
1'
1!
#3500000
b0 (
0!
1%
#3550000
b1 (
0'
b0 &
1!
#3600000
b0 (
0!
0%
#3650000
1'
1!
#3700000
0!
#3750000
1!
#3800000
0!
#3850000
1!
#3900000
0!
#3950000
1!
#4000000
0!
#4050000
1!
#4100000
0!
1$
#4150000
1!
#4200000
0!
0$
