divisor/divisor.v
module divisor(
	input wire clk,
	input wire reset,
	input wire [3:0] A,
	input wire [3:0] B,
	output wire [3:0] S,
	output wire [3:0] R
);

localparam [1:0] S0= 2'b00, S1= 2'b01;
	
reg [1:0] state, nextstate;

reg [3:0] resto;
reg [3:0] contador=0;
reg bandera=0;

always @(posedge clk, posedge reset)
	begin	
		if(reset)
			begin 
				state <=S0;
			end
		else	
			begin 
				state <= nextstate; 
			end
	end

always @*
		begin
			if (bandera==0)
				begin
					resto=A;
					bandera=1;
				end
					nextstate = state;
				case(state)
					S0: if(resto>B)
							nextstate=S0;
						else
							nextstate=S1;			
					default:
							nextstate=state;
				endcase
		end


always @*
		begin
			nextstate = state;
				
			case(state)
					S0: if(clk && resto>0)
							begin
								resto= resto - B;
								contador=contador+1;
							end
			endcase
		end

assign S=contador;	
assign R=resto;

endmodule

divisor/divisor_tb.v
`default_nettype none
`define DUMPSTR(x) `"x.vcd`"
`timescale 100 ns / 10 ns 

//timescale <time_unit> / <time_precision>

module divisor_tb();

//-- Simulation time: 1us (10 * 100ns)
parameter DURATION = 10;

//-- Clock signal. It is not used in this simulation
reg clk =0;
always #0.5 clk = ~clk;

reg [3:0] test_A_in;
reg [3:0] test_B_in;
wire [3:0] test_S_out;
wire [3:0] test_R_out;
reg test_rst;

//-- Instantiate the unit to test
divisor UUT(
			.clk(clk),
			.reset(test_rst),
			.A(test_A_in),
			.B(test_B_in),
			.S(test_S_out),
			.R(test_R_out)
			);

initial begin

//-- File were to store the simulation result
$dumpfile(`DUMPSTR(`VCD_OUTPUT));
$dumpvars(0, divisor_tb);

		test_A_in = 15;
		test_B_in = 3;


	
	
	test_rst=1'b1;
	#5
	test_rst=1'b0;
	#5
	test_rst=1'b1;
	#5
	test_rst=1'b0;
	#5
	test_rst=1'b1;
	#5
	test_rst=1'b0;
	#5
	test_rst=1'b1;
	#5
	test_rst=1'b0;
	#5
		test_rst=1'b1;
	#5
	test_rst=1'b0;
	#5
	test_rst=1'b1;
	#5
	test_rst=1'b0;
	#5
	
	$finish;
	
	#(DURATION) $display("End of Simulation");
	$finish;
	
end

endmodule

divisor/divisor_tb.vcd
$date
	Mon Jun 12 13:53:20 2023
$end
$version
	Icarus Verilog
$end
$timescale
	1ps
$end
$scope module divisor_tb $end
$var wire 4 ! test_S_out [3:0] $end
$var wire 4 " test_R_out [3:0] $end
$var reg 1 # clk $end
$var reg 4 $ test_A_in [3:0] $end
$var reg 4 % test_B_in [3:0] $end
$var reg 1 & test_rst $end
$scope module UUT $end
$var wire 4 ' A [3:0] $end
$var wire 4 ( B [3:0] $end
$var wire 4 ) R [3:0] $end
$var wire 4 * S [3:0] $end
$var wire 1 # clk $end
$var wire 1 & reset $end
$var reg 1 + bandera $end
$var reg 4 , contador [3:0] $end
$var reg 2 - nextstate [1:0] $end
$var reg 4 . resto [3:0] $end
$var reg 2 / state [1:0] $end
$upscope $end
$upscope $end
$enddefinitions $end
#0
$dumpvars
b0 /
b1111 .
b0 -
b0 ,
1+
b0 *
b1111 )
b11 (
b1111 '
1&
b11 %
b1111 $
0#
b1111 "
b0 !
$end
#50000
b1 !
b1 *
b1 ,
b1100 "
b1100 )
b1100 .
1#
#100000
0#
#150000
b10 !
b10 *
b10 ,
b1001 "
b1001 )
b1001 .
1#
#200000
0#
#250000
b11 !
b11 *
b11 ,
b110 "
b110 )
b110 .
1#
#300000
0#
#350000
b1 -
b100 !
b100 *
b100 ,
b11 "
b11 )
b11 .
1#
#400000
b0 -
0#
#450000
b1 -
b101 !
b101 *
b101 ,
b0 "
b0 )
b0 .
1#
#500000
b0 -
0#
0&
#550000
1#
#600000
0#
#650000
1#
#700000
0#
#750000
1#
#800000
0#
#850000
1#
#900000
0#
#950000
1#
#1000000
0#
1&
#1050000
1#
#1100000
0#
#1150000
1#
#1200000
0#
#1250000
1#
#1300000
0#
#1350000
1#
#1400000
0#
#1450000
1#
#1500000
0#
0&
#1550000
1#
#1600000
0#
#1650000
1#
#1700000
0#
#1750000
1#
#1800000
0#
#1850000
1#
#1900000
0#
#1950000
1#
#2000000
0#
1&
#2050000
1#
#2100000
0#
#2150000
1#
#2200000
0#
#2250000
1#
#2300000
0#
#2350000
1#
#2400000
0#
#2450000
1#
#2500000
0#
0&
#2550000
1#
#2600000
0#
#2650000
1#
#2700000
0#
#2750000
1#
#2800000
0#
#2850000
1#
#2900000
0#
#2950000
1#
#3000000
0#
1&
#3050000
1#
#3100000
0#
#3150000
1#
#3200000
0#
#3250000
1#
#3300000
0#
#3350000
1#
#3400000
0#
#3450000
1#
#3500000
0#
0&
#3550000
1#
#3600000
0#
#3650000
1#
#3700000
0#
#3750000
1#
#3800000
0#
#3850000
1#
#3900000
0#
#3950000
1#
#4000000
0#
1&
#4050000
1#
#4100000
0#
#4150000
1#
#4200000
0#
#4250000
1#
#4300000
0#
#4350000
1#
#4400000
0#
#4450000
1#
#4500000
0#
0&
#4550000
1#
#4600000
0#
#4650000
1#
#4700000
0#
#4750000
1#
#4800000
0#
#4850000
1#
#4900000
0#
#4950000
1#
#5000000
0#
1&
#5050000
1#
#5100000
0#
#5150000
1#
#5200000
0#
#5250000
1#
#5300000
0#
#5350000
1#
#5400000
0#
#5450000
1#
#5500000
0#
0&
