divisor/divisor.v
module divisor(
	input wire clk, rst,
	input wire [3:0] A,
	input wire [3:0] B,
	output reg [3:0] S,
	output reg [3:0] R
);
	
	
localparam [1:0] 
	espera = 2'b00,
	error = 2'b01,
	resta = 2'b10,
	fin = 2'b11;
	
reg [1:0] state, next_state;
reg [3:0] A_reg, next_A, iteracion;


always @(posedge clk)
	begin	
		if(rst)
			begin 
				state <= espera;
			end
		else
			begin
				A_reg <= next_A;
				state <= next_state;
			end
	end


always @*
	case(state)
		espera :
			begin
				if(A < B | B == 0) 
					next_state <= error;
				else 
					next_state <= resta;
					next_A <= A;
					iteracion <= 0;
			end
		 resta :		
			if(A_reg < B)
				next_state <= fin;
			else
				begin
					next_state <= resta;
					next_A <= A_reg-B;
					iteracion++;
				end
		fin :
			begin
				next_state <= fin;
				next_A <= R;
				S <= iteracion;
				R <= A_reg;
			end
	endcase
endmodule

divisor/divisor_tb.v
`default_nettype none
`define DUMPSTR(x) `"x.vcd`"
`timescale 100 ns / 10 ns 

//timescale <time_unit> / <time_precision>

module divisor_tb();

//-- Simulation time: 1us (10 * 100ns)
parameter DURATION = 10;

//-- Clock signal. It is not used in this simulation
reg clk =0;
always #0.5 clk = ~clk;

reg [3:0] test_A;
reg [3:0] test_B;
wire [3:0] test_S;
wire [3:0] test_R;
reg test_rst;

//-- Instantiate the unit to test
divisor UUT(
			.clk(clk),
			.rst(test_rst),
			.A(test_A),
			.B(test_B),
			.S(test_S),
			.R(test_R)
			);

initial begin

//-- File were to store the simulation result
$dumpfile(`DUMPSTR(`VCD_OUTPUT));
$dumpvars(0, divisor_tb);
	test_A = 14;
	test_B = 3;
	#1
	test_rst = 1'b1;
	#1
	test_rst = 1'b0;
	#10
	
	$finish;
	
	#(DURATION) $display("End of Simulation");
	$finish;
	
end

endmodule

divisor/divisor_tb.vcd
$date
	Fri Jun 16 11:51:25 2023
$end
$version
	Icarus Verilog
$end
$timescale
	1ps
$end
$scope module divisor_tb $end
$var wire 4 ! test_S [3:0] $end
$var wire 4 " test_R [3:0] $end
$var reg 1 # clk $end
$var reg 4 $ test_A [3:0] $end
$var reg 4 % test_B [3:0] $end
$var reg 1 & test_rst $end
$scope module UUT $end
$var wire 4 ' A [3:0] $end
$var wire 4 ( B [3:0] $end
$var wire 1 # clk $end
$var wire 1 & rst $end
$var reg 4 ) A_reg [3:0] $end
$var reg 4 * R [3:0] $end
$var reg 4 + S [3:0] $end
$var reg 4 , iteracion [3:0] $end
$var reg 4 - next_A [3:0] $end
$var reg 2 . next_state [1:0] $end
$var reg 2 / state [1:0] $end
$upscope $end
$upscope $end
$enddefinitions $end
#0
$dumpvars
bx /
bx .
bx -
bx ,
bx +
bx *
bx )
b11 (
b1110 '
x&
b11 %
b1110 $
0#
bx "
bx !
$end
#50000
1#
#100000
0#
1&
#150000
b0 ,
b1110 -
b10 .
b0 /
1#
#200000
0#
0&
#250000
b1011 -
b1 ,
b10 /
b1110 )
1#
#300000
0#
#350000
b1000 -
b10 ,
b1011 )
1#
#400000
0#
#450000
b101 -
b11 ,
b1000 )
1#
#500000
0#
#550000
b10 -
b100 ,
b101 )
1#
#600000
0#
#650000
b11 .
b10 )
1#
#700000
0#
#750000
b10 "
b10 *
b100 !
b100 +
b10 -
b11 /
1#
