flip_flop_d_rst_en/flip_flop_d_rst_en.v
module flip_flop_d_rst_en(
	input wire D, rst, en,
	input wire clk,
	output reg Q
);

always @(posedge clk) begin
	if(rst) Q <= 1'b0;
	else if (en) Q <= D;
end

endmodule

flip_flop_d_rst_en/flip_flop_d_rst_en_tb.v
`default_nettype none
`define DUMPSTR(x) `"x.vcd`"
`timescale 100 ns / 10 ns

module flip_flop_d_rst_en_tb();

parameter DURATION = 10;

reg clk = 0;
always #0.5 clk = ~clk; //cada 0.5 unidades temporales se niega el clk

reg test_D, test_rst, test_en;
wire test_Q;

flip_flop_d_rst_en UUT (//-- Instantiate the unit to test
	.clk(clk),
	.rst(test_rst),
	.D(test_D),
	.Q(test_Q),
	.en(test_en)
);


initial begin
	$dumpfile(`DUMPSTR(`VCD_OUTPUT));//-- File were to store the simulation results
	$dumpvars(0, flip_flop_d_rst_en_tb);
		
		test_en=0;
		test_rst = 0;
		#1
		test_D = 0;
		#5
		test_D = 1;
		#2
		test_rst = 1;
		#2
		test_rst = 0;
		#3
		test_en = 1;
		#7
		test_D = 0;
	
	#(DURATION);
	$finish;
end

endmodule

flip_flop_d_rst_en/flip_flop_d_rst_en_tb.vcd
$date
	Thu Jun 08 15:49:38 2023
$end
$version
	Icarus Verilog
$end
$timescale
	1ps
$end
$scope module flip_flop_d_rst_en_tb $end
$var wire 1 ! test_Q $end
$var reg 1 " clk $end
$var reg 1 # test_D $end
$var reg 1 $ test_en $end
$var reg 1 % test_rst $end
$scope module UUT $end
$var wire 1 # D $end
$var wire 1 " clk $end
$var wire 1 $ en $end
$var wire 1 % rst $end
$var reg 1 ! Q $end
$upscope $end
$upscope $end
$enddefinitions $end
#0
$dumpvars
0%
0$
x#
0"
x!
$end
#50000
1"
#100000
0"
0#
#150000
1"
#200000
0"
#250000
1"
#300000
0"
#350000
1"
#400000
0"
#450000
1"
#500000
0"
#550000
1"
#600000
0"
1#
#650000
1"
#700000
0"
#750000
1"
#800000
0"
1%
#850000
0!
1"
#900000
0"
#950000
1"
#1000000
0"
0%
#1050000
1"
#1100000
0"
#1150000
1"
#1200000
0"
#1250000
1"
#1300000
0"
1$
#1350000
1!
1"
#1400000
0"
#1450000
1"
#1500000
0"
#1550000
1"
#1600000
0"
#1650000
1"
#1700000
0"
#1750000
1"
#1800000
0"
#1850000
1"
#1900000
0"
#1950000
1"
#2000000
0"
0#
#2050000
0!
1"
